pscript/__init__.py
pscript/config.py
pscript/context.py
pscript/function_analyzer.py
pscript/log_config.py
pscript/model_registry.py
pscript/persistence.py
pscript/prompt.py
pscript/promptscript-defaults.yml
pscript/schema_builder.py
pscript/tracer.py
pscript/types.py
pscript/utils.py
pscript/providers/__init__.py
pscript/providers/anthropic.py
pscript/providers/azure_openai.py
pscript/providers/base.py
pscript/providers/deepseek.py
pscript/providers/gemini.py
pscript/providers/mlx.py
pscript/providers/ollama.py
pscript/providers/openai.py
pscript/providers/openrouter.py
promptscript_python-0.4.4.dist-info/METADATA
promptscript_python-0.4.4.dist-info/WHEEL
promptscript_python-0.4.4.dist-info/entry_points.txt
promptscript_python-0.4.4.dist-info/top_level.txt
promptscript_python-0.4.4.dist-info/RECORD
