Metadata-Version: 2.4
Name: promptscript-python
Version: 0.4.4
Summary: A library for writing LLM prompts as Python functions
Author-email: John Lam <jflam@microsoft.com>
License: MIT
Project-URL: Homepage, https://github.com/jflam/promptscript
Requires-Python: >=3.12
Requires-Dist: azure-identity>=1.21.0
Requires-Dist: openai>=1.62.0
Requires-Dist: anthropic>=0.45.2
Requires-Dist: google-genai>=1.2.0
Requires-Dist: pytest>=8.3.4
Requires-Dist: filelock>=3.17.0
Requires-Dist: pyyaml>=6.0.2
Requires-Dist: pillow>=11.1.0
Requires-Dist: tenacity>=9.0.0
Requires-Dist: pytest-cov>=6.0.0
Requires-Dist: pytest-xdist>=3.6.1
